graphsLuicazen/__init__.py
graphsLuicazen/heapq.py
graphsLuicazen/sp.py
graphsluicazen-0.0.1.dist-info/METADATA
graphsluicazen-0.0.1.dist-info/WHEEL
graphsluicazen-0.0.1.dist-info/RECORD
